wando
